/*     */ package net.craftersland.customenderchest.storage;
/*     */ 
/*     */ import java.sql.Connection;
/*     */ import java.sql.DriverManager;
/*     */ import java.sql.SQLException;
/*     */ import java.util.Properties;
/*     */ import java.util.logging.Logger;
/*     */ import net.craftersland.customenderchest.ConfigHandler;
/*     */ import net.craftersland.customenderchest.EnderChest;
/*     */ import org.bukkit.Bukkit;
/*     */ import org.bukkit.scheduler.BukkitScheduler;
/*     */ 
/*     */ 
/*     */ 
/*     */ public class MysqlSetup
/*     */ {
/*  17 */   private Connection conn = null;
/*     */   private EnderChest enderchest;
/*  19 */   private boolean tablesChecked = false;
/*     */   
/*     */   public MysqlSetup(EnderChest enderchest) {
/*  22 */     this.enderchest = enderchest;
/*  23 */     setupDatabase();
/*  24 */     updateTables();
/*     */   }
/*     */   
/*     */   public void setupDatabase() {
/*  28 */     connectToDatabase();
/*  29 */     databaseMaintenanceTask();
/*     */   }
/*     */   
/*     */   /* Error */
/*     */   private void tableMaintenance(long inactiveTime, Connection conn, String tableName)
/*     */   {
/*     */     // Byte code:
/*     */     //   0: aconst_null
/*     */     //   1: astore 5
/*     */     //   3: new 41	java/lang/StringBuilder
/*     */     //   6: dup
/*     */     //   7: ldc 43
/*     */     //   9: invokespecial 45	java/lang/StringBuilder:<init>	(Ljava/lang/String;)V
/*     */     //   12: aload 4
/*     */     //   14: invokevirtual 48	java/lang/StringBuilder:append	(Ljava/lang/String;)Ljava/lang/StringBuilder;
/*     */     //   17: ldc 52
/*     */     //   19: invokevirtual 48	java/lang/StringBuilder:append	(Ljava/lang/String;)Ljava/lang/StringBuilder;
/*     */     //   22: invokevirtual 54	java/lang/StringBuilder:toString	()Ljava/lang/String;
/*     */     //   25: astore 6
/*     */     //   27: aload_3
/*     */     //   28: aload 6
/*     */     //   30: invokeinterface 58 2 0
/*     */     //   35: astore 5
/*     */     //   37: aload 5
/*     */     //   39: iconst_1
/*     */     //   40: lload_1
/*     */     //   41: invokestatic 64	java/lang/String:valueOf	(J)Ljava/lang/String;
/*     */     //   44: invokeinterface 70 3 0
/*     */     //   49: aload 5
/*     */     //   51: invokeinterface 76 1 0
/*     */     //   56: pop
/*     */     //   57: goto +62 -> 119
/*     */     //   60: astore 6
/*     */     //   62: aload 6
/*     */     //   64: invokevirtual 80	java/lang/Exception:printStackTrace	()V
/*     */     //   67: aload 5
/*     */     //   69: ifnull +72 -> 141
/*     */     //   72: aload 5
/*     */     //   74: invokeinterface 85 1 0
/*     */     //   79: goto +62 -> 141
/*     */     //   82: astore 8
/*     */     //   84: aload 8
/*     */     //   86: invokevirtual 80	java/lang/Exception:printStackTrace	()V
/*     */     //   89: goto +52 -> 141
/*     */     //   92: astore 7
/*     */     //   94: aload 5
/*     */     //   96: ifnull +20 -> 116
/*     */     //   99: aload 5
/*     */     //   101: invokeinterface 85 1 0
/*     */     //   106: goto +10 -> 116
/*     */     //   109: astore 8
/*     */     //   111: aload 8
/*     */     //   113: invokevirtual 80	java/lang/Exception:printStackTrace	()V
/*     */     //   116: aload 7
/*     */     //   118: athrow
/*     */     //   119: aload 5
/*     */     //   121: ifnull +20 -> 141
/*     */     //   124: aload 5
/*     */     //   126: invokeinterface 85 1 0
/*     */     //   131: goto +10 -> 141
/*     */     //   134: astore 8
/*     */     //   136: aload 8
/*     */     //   138: invokevirtual 80	java/lang/Exception:printStackTrace	()V
/*     */     //   141: return
/*     */     // Line number table:
/*     */     //   Java source line #33	-> byte code offset #0
/*     */     //   Java source line #35	-> byte code offset #3
/*     */     //   Java source line #36	-> byte code offset #27
/*     */     //   Java source line #37	-> byte code offset #37
/*     */     //   Java source line #38	-> byte code offset #49
/*     */     //   Java source line #39	-> byte code offset #57
/*     */     //   Java source line #40	-> byte code offset #62
/*     */     //   Java source line #43	-> byte code offset #67
/*     */     //   Java source line #44	-> byte code offset #72
/*     */     //   Java source line #46	-> byte code offset #79
/*     */     //   Java source line #47	-> byte code offset #84
/*     */     //   Java source line #41	-> byte code offset #92
/*     */     //   Java source line #43	-> byte code offset #94
/*     */     //   Java source line #44	-> byte code offset #99
/*     */     //   Java source line #46	-> byte code offset #106
/*     */     //   Java source line #47	-> byte code offset #111
/*     */     //   Java source line #49	-> byte code offset #116
/*     */     //   Java source line #43	-> byte code offset #119
/*     */     //   Java source line #44	-> byte code offset #124
/*     */     //   Java source line #46	-> byte code offset #131
/*     */     //   Java source line #47	-> byte code offset #136
/*     */     //   Java source line #50	-> byte code offset #141
/*     */     // Local variable table:
/*     */     //   start	length	slot	name	signature
/*     */     //   0	142	0	this	MysqlSetup
/*     */     //   0	142	1	inactiveTime	long
/*     */     //   0	142	3	conn	Connection
/*     */     //   0	142	4	tableName	String
/*     */     //   1	124	5	preparedStatement	java.sql.PreparedStatement
/*     */     //   25	4	6	sql	String
/*     */     //   60	3	6	e	Exception
/*     */     //   92	25	7	localObject	Object
/*     */     //   82	3	8	e	Exception
/*     */     //   109	3	8	e	Exception
/*     */     //   134	3	8	e	Exception
/*     */     // Exception table:
/*     */     //   from	to	target	type
/*     */     //   3	57	60	java/lang/Exception
/*     */     //   67	79	82	java/lang/Exception
/*     */     //   3	67	92	finally
/*     */     //   94	106	109	java/lang/Exception
/*     */     //   119	131	134	java/lang/Exception
/*     */   }
/*     */   
/*     */   private void databaseMaintenanceTask()
/*     */   {
/*  53 */     if (this.enderchest.getConfigHandler().getBoolean("database.mysql.removeOldUsers.enabled")) {
/*  54 */       Bukkit.getScheduler().runTaskLaterAsynchronously(this.enderchest, new Runnable()
/*     */       {
/*     */         public void run()
/*     */         {
/*  58 */           if (MysqlSetup.this.conn != null) {
/*  59 */             long inactivityDays = Long.parseLong(MysqlSetup.this.enderchest.getConfigHandler().getString("database.mysql.removeOldUsers.inactive"));
/*  60 */             long inactivityMils = inactivityDays * 24L * 60L * 60L * 1000L;
/*  61 */             long curentTime = System.currentTimeMillis();
/*  62 */             long inactiveTime = curentTime - inactivityMils;
/*  63 */             EnderChest.log.info("Database maintenance task started...");
/*  64 */             MysqlSetup.this.tableMaintenance(inactiveTime, MysqlSetup.this.getConnection(), MysqlSetup.this.enderchest.getConfigHandler().getString("database.mysql.tableName"));
/*  65 */             EnderChest.log.info("Database maintenance complete!");
/*     */           }
/*     */           
/*     */         }
/*  69 */       }, 2000L);
/*     */     }
/*     */   }
/*     */   
/*     */   private void connectToDatabase()
/*     */   {
/*     */     try {
/*  76 */       Class.forName("com.mysql.jdbc.Driver");
/*     */       
/*  78 */       Properties properties = new Properties();
/*  79 */       properties.setProperty("user", this.enderchest.getConfigHandler().getString("database.mysql.user"));
/*  80 */       properties.setProperty("password", this.enderchest.getConfigHandler().getString("database.mysql.password"));
/*  81 */       properties.setProperty("autoReconnect", "true");
/*  82 */       properties.setProperty("verifyServerCertificate", "false");
/*  83 */       properties.setProperty("useSSL", this.enderchest.getConfigHandler().getString("database.mysql.ssl"));
/*  84 */       properties.setProperty("requireSSL", this.enderchest.getConfigHandler().getString("database.mysql.ssl"));
/*     */       
/*     */ 
/*  87 */       this.conn = DriverManager.getConnection("jdbc:mysql://" + this.enderchest.getConfigHandler().getString("database.mysql.host") + ":" + this.enderchest.getConfigHandler().getString("database.mysql.port") + "/" + this.enderchest.getConfigHandler().getString("database.mysql.databaseName"), properties);
/*  88 */       EnderChest.log.info("Database connection established!");
/*  89 */       if (!this.tablesChecked) {
/*  90 */         setupTables();
/*     */       }
/*     */     } catch (ClassNotFoundException e) {
/*  93 */       EnderChest.log.severe("Could not locate drivers for mysql! Error: " + e.getMessage());
/*     */     } catch (SQLException e) {
/*  95 */       EnderChest.log.severe("Could not connect to mysql database! Error: " + e.getMessage());
/*     */     } catch (Exception ex) {
/*  97 */       EnderChest.log.severe("Could not connect to mysql database! Error: " + ex.getMessage());
/*  98 */       ex.printStackTrace();
/*     */     }
/*     */   }
/*     */   
/*     */   /* Error */
/*     */   public void setupTables()
/*     */   {
/*     */     // Byte code:
/*     */     //   0: aload_0
/*     */     //   1: getfield 17	net/craftersland/customenderchest/storage/MysqlSetup:conn	Ljava/sql/Connection;
/*     */     //   4: ifnull +160 -> 164
/*     */     //   7: aconst_null
/*     */     //   8: astore_1
/*     */     //   9: new 41	java/lang/StringBuilder
/*     */     //   12: dup
/*     */     //   13: ldc -29
/*     */     //   15: invokespecial 45	java/lang/StringBuilder:<init>	(Ljava/lang/String;)V
/*     */     //   18: aload_0
/*     */     //   19: getfield 21	net/craftersland/customenderchest/storage/MysqlSetup:enderchest	Lnet/craftersland/customenderchest/EnderChest;
/*     */     //   22: invokevirtual 100	net/craftersland/customenderchest/EnderChest:getConfigHandler	()Lnet/craftersland/customenderchest/ConfigHandler;
/*     */     //   25: ldc -27
/*     */     //   27: invokevirtual 148	net/craftersland/customenderchest/ConfigHandler:getString	(Ljava/lang/String;)Ljava/lang/String;
/*     */     //   30: invokevirtual 48	java/lang/StringBuilder:append	(Ljava/lang/String;)Ljava/lang/StringBuilder;
/*     */     //   33: ldc -25
/*     */     //   35: invokevirtual 48	java/lang/StringBuilder:append	(Ljava/lang/String;)Ljava/lang/StringBuilder;
/*     */     //   38: invokevirtual 54	java/lang/StringBuilder:toString	()Ljava/lang/String;
/*     */     //   41: astore_2
/*     */     //   42: aload_0
/*     */     //   43: getfield 17	net/craftersland/customenderchest/storage/MysqlSetup:conn	Ljava/sql/Connection;
/*     */     //   46: aload_2
/*     */     //   47: invokeinterface 58 2 0
/*     */     //   52: astore_1
/*     */     //   53: aload_1
/*     */     //   54: invokeinterface 76 1 0
/*     */     //   59: pop
/*     */     //   60: aload_0
/*     */     //   61: iconst_1
/*     */     //   62: putfield 19	net/craftersland/customenderchest/storage/MysqlSetup:tablesChecked	Z
/*     */     //   65: goto +79 -> 144
/*     */     //   68: astore_2
/*     */     //   69: getstatic 192	net/craftersland/customenderchest/EnderChest:log	Ljava/util/logging/Logger;
/*     */     //   72: new 41	java/lang/StringBuilder
/*     */     //   75: dup
/*     */     //   76: ldc -23
/*     */     //   78: invokespecial 45	java/lang/StringBuilder:<init>	(Ljava/lang/String;)V
/*     */     //   81: aload_2
/*     */     //   82: invokevirtual 221	java/lang/Exception:getMessage	()Ljava/lang/String;
/*     */     //   85: invokevirtual 48	java/lang/StringBuilder:append	(Ljava/lang/String;)Ljava/lang/StringBuilder;
/*     */     //   88: invokevirtual 54	java/lang/StringBuilder:toString	()Ljava/lang/String;
/*     */     //   91: invokevirtual 213	java/util/logging/Logger:severe	(Ljava/lang/String;)V
/*     */     //   94: aload_2
/*     */     //   95: invokevirtual 80	java/lang/Exception:printStackTrace	()V
/*     */     //   98: aload_1
/*     */     //   99: ifnull +65 -> 164
/*     */     //   102: aload_1
/*     */     //   103: invokeinterface 85 1 0
/*     */     //   108: goto +56 -> 164
/*     */     //   111: astore 4
/*     */     //   113: aload 4
/*     */     //   115: invokevirtual 80	java/lang/Exception:printStackTrace	()V
/*     */     //   118: goto +46 -> 164
/*     */     //   121: astore_3
/*     */     //   122: aload_1
/*     */     //   123: ifnull +19 -> 142
/*     */     //   126: aload_1
/*     */     //   127: invokeinterface 85 1 0
/*     */     //   132: goto +10 -> 142
/*     */     //   135: astore 4
/*     */     //   137: aload 4
/*     */     //   139: invokevirtual 80	java/lang/Exception:printStackTrace	()V
/*     */     //   142: aload_3
/*     */     //   143: athrow
/*     */     //   144: aload_1
/*     */     //   145: ifnull +19 -> 164
/*     */     //   148: aload_1
/*     */     //   149: invokeinterface 85 1 0
/*     */     //   154: goto +10 -> 164
/*     */     //   157: astore 4
/*     */     //   159: aload 4
/*     */     //   161: invokevirtual 80	java/lang/Exception:printStackTrace	()V
/*     */     //   164: return
/*     */     // Line number table:
/*     */     //   Java source line #103	-> byte code offset #0
/*     */     //   Java source line #104	-> byte code offset #7
/*     */     //   Java source line #106	-> byte code offset #9
/*     */     //   Java source line #107	-> byte code offset #42
/*     */     //   Java source line #108	-> byte code offset #53
/*     */     //   Java source line #109	-> byte code offset #60
/*     */     //   Java source line #110	-> byte code offset #65
/*     */     //   Java source line #111	-> byte code offset #69
/*     */     //   Java source line #112	-> byte code offset #94
/*     */     //   Java source line #115	-> byte code offset #98
/*     */     //   Java source line #116	-> byte code offset #102
/*     */     //   Java source line #118	-> byte code offset #108
/*     */     //   Java source line #119	-> byte code offset #113
/*     */     //   Java source line #113	-> byte code offset #121
/*     */     //   Java source line #115	-> byte code offset #122
/*     */     //   Java source line #116	-> byte code offset #126
/*     */     //   Java source line #118	-> byte code offset #132
/*     */     //   Java source line #119	-> byte code offset #137
/*     */     //   Java source line #121	-> byte code offset #142
/*     */     //   Java source line #115	-> byte code offset #144
/*     */     //   Java source line #116	-> byte code offset #148
/*     */     //   Java source line #118	-> byte code offset #154
/*     */     //   Java source line #119	-> byte code offset #159
/*     */     //   Java source line #123	-> byte code offset #164
/*     */     // Local variable table:
/*     */     //   start	length	slot	name	signature
/*     */     //   0	165	0	this	MysqlSetup
/*     */     //   8	141	1	query1	java.sql.PreparedStatement
/*     */     //   41	6	2	data	String
/*     */     //   68	27	2	e	Exception
/*     */     //   121	22	3	localObject	Object
/*     */     //   111	3	4	e	Exception
/*     */     //   135	3	4	e	Exception
/*     */     //   157	3	4	e	Exception
/*     */     // Exception table:
/*     */     //   from	to	target	type
/*     */     //   9	65	68	java/lang/Exception
/*     */     //   98	108	111	java/lang/Exception
/*     */     //   9	98	121	finally
/*     */     //   122	132	135	java/lang/Exception
/*     */     //   144	154	157	java/lang/Exception
/*     */   }
/*     */   
/*     */   public Connection getConnection()
/*     */   {
/* 126 */     checkConnection();
/* 127 */     return this.conn;
/*     */   }
/*     */   
/*     */   public void closeConnection() {
/*     */     try {
/* 132 */       EnderChest.log.info("Closing database connection...");
/* 133 */       if (this.conn != null) {
/* 134 */         this.conn.close();
/* 135 */         this.conn = null;
/*     */       }
/*     */     } catch (SQLException e) {
/* 138 */       e.printStackTrace();
/*     */     }
/*     */   }
/*     */   
/*     */   private void checkConnection() {
/*     */     try {
/* 144 */       if (this.conn == null) {
/* 145 */         EnderChest.log.warning("Database connection failed. Reconnecting...");
/* 146 */         this.conn = null;
/* 147 */         connectToDatabase();
/* 148 */       } else if (!this.conn.isValid(3)) {
/* 149 */         EnderChest.log.warning("Database connection failed. Reconnecting...");
/* 150 */         this.conn = null;
/* 151 */         connectToDatabase();
/* 152 */       } else if (this.conn.isClosed()) {
/* 153 */         EnderChest.log.warning("Database connection failed. Reconnecting...");
/* 154 */         this.conn = null;
/* 155 */         connectToDatabase();
/*     */       }
/*     */     } catch (Exception e) {
/* 158 */       EnderChest.log.severe("Error re-connecting to the database! Error: " + e.getMessage());
/*     */     }
/*     */   }
/*     */   
/*     */   public boolean closeDatabase() {
/*     */     try {
/* 164 */       this.conn.close();
/* 165 */       this.conn = null;
/* 166 */       return true;
/*     */     } catch (SQLException e) {
/* 168 */       e.printStackTrace();
/*     */     }
/* 170 */     return false;
/*     */   }
/*     */   
/*     */   /* Error */
/*     */   private void updateTables()
/*     */   {
/*     */     // Byte code:
/*     */     //   0: aload_0
/*     */     //   1: getfield 17	net/craftersland/customenderchest/storage/MysqlSetup:conn	Ljava/sql/Connection;
/*     */     //   4: ifnull +433 -> 437
/*     */     //   7: aconst_null
/*     */     //   8: astore_1
/*     */     //   9: aconst_null
/*     */     //   10: astore_2
/*     */     //   11: aconst_null
/*     */     //   12: astore_3
/*     */     //   13: aconst_null
/*     */     //   14: astore 4
/*     */     //   16: aconst_null
/*     */     //   17: astore 5
/*     */     //   19: aload_0
/*     */     //   20: getfield 17	net/craftersland/customenderchest/storage/MysqlSetup:conn	Ljava/sql/Connection;
/*     */     //   23: invokeinterface 261 1 0
/*     */     //   28: astore_1
/*     */     //   29: aload_1
/*     */     //   30: aconst_null
/*     */     //   31: aconst_null
/*     */     //   32: aload_0
/*     */     //   33: getfield 21	net/craftersland/customenderchest/storage/MysqlSetup:enderchest	Lnet/craftersland/customenderchest/EnderChest;
/*     */     //   36: invokevirtual 100	net/craftersland/customenderchest/EnderChest:getConfigHandler	()Lnet/craftersland/customenderchest/ConfigHandler;
/*     */     //   39: ldc -27
/*     */     //   41: invokevirtual 148	net/craftersland/customenderchest/ConfigHandler:getString	(Ljava/lang/String;)Ljava/lang/String;
/*     */     //   44: ldc_w 265
/*     */     //   47: invokeinterface 266 5 0
/*     */     //   52: astore_2
/*     */     //   53: aload_2
/*     */     //   54: invokeinterface 272 1 0
/*     */     //   59: ifeq +63 -> 122
/*     */     //   62: new 41	java/lang/StringBuilder
/*     */     //   65: dup
/*     */     //   66: ldc_w 277
/*     */     //   69: invokespecial 45	java/lang/StringBuilder:<init>	(Ljava/lang/String;)V
/*     */     //   72: aload_0
/*     */     //   73: getfield 21	net/craftersland/customenderchest/storage/MysqlSetup:enderchest	Lnet/craftersland/customenderchest/EnderChest;
/*     */     //   76: invokevirtual 100	net/craftersland/customenderchest/EnderChest:getConfigHandler	()Lnet/craftersland/customenderchest/ConfigHandler;
/*     */     //   79: ldc -27
/*     */     //   81: invokevirtual 148	net/craftersland/customenderchest/ConfigHandler:getString	(Ljava/lang/String;)Ljava/lang/String;
/*     */     //   84: invokevirtual 48	java/lang/StringBuilder:append	(Ljava/lang/String;)Ljava/lang/StringBuilder;
/*     */     //   87: ldc_w 279
/*     */     //   90: invokevirtual 48	java/lang/StringBuilder:append	(Ljava/lang/String;)Ljava/lang/StringBuilder;
/*     */     //   93: invokevirtual 54	java/lang/StringBuilder:toString	()Ljava/lang/String;
/*     */     //   96: astore 6
/*     */     //   98: aload_0
/*     */     //   99: getfield 17	net/craftersland/customenderchest/storage/MysqlSetup:conn	Ljava/sql/Connection;
/*     */     //   102: aload 6
/*     */     //   104: invokeinterface 58 2 0
/*     */     //   109: astore 4
/*     */     //   111: aload 4
/*     */     //   113: invokeinterface 76 1 0
/*     */     //   118: pop
/*     */     //   119: goto +264 -> 383
/*     */     //   122: aload_1
/*     */     //   123: aconst_null
/*     */     //   124: aconst_null
/*     */     //   125: aload_0
/*     */     //   126: getfield 21	net/craftersland/customenderchest/storage/MysqlSetup:enderchest	Lnet/craftersland/customenderchest/EnderChest;
/*     */     //   129: invokevirtual 100	net/craftersland/customenderchest/EnderChest:getConfigHandler	()Lnet/craftersland/customenderchest/ConfigHandler;
/*     */     //   132: ldc -27
/*     */     //   134: invokevirtual 148	net/craftersland/customenderchest/ConfigHandler:getString	(Ljava/lang/String;)Ljava/lang/String;
/*     */     //   137: ldc_w 281
/*     */     //   140: invokeinterface 266 5 0
/*     */     //   145: astore_3
/*     */     //   146: aload_3
/*     */     //   147: invokeinterface 272 1 0
/*     */     //   152: ifeq +231 -> 383
/*     */     //   155: aload_3
/*     */     //   156: ldc_w 283
/*     */     //   159: invokeinterface 285 2 0
/*     */     //   164: ldc_w 286
/*     */     //   167: invokevirtual 288	java/lang/String:matches	(Ljava/lang/String;)Z
/*     */     //   170: ifeq +213 -> 383
/*     */     //   173: new 41	java/lang/StringBuilder
/*     */     //   176: dup
/*     */     //   177: ldc_w 277
/*     */     //   180: invokespecial 45	java/lang/StringBuilder:<init>	(Ljava/lang/String;)V
/*     */     //   183: aload_0
/*     */     //   184: getfield 21	net/craftersland/customenderchest/storage/MysqlSetup:enderchest	Lnet/craftersland/customenderchest/EnderChest;
/*     */     //   187: invokevirtual 100	net/craftersland/customenderchest/EnderChest:getConfigHandler	()Lnet/craftersland/customenderchest/ConfigHandler;
/*     */     //   190: ldc -27
/*     */     //   192: invokevirtual 148	net/craftersland/customenderchest/ConfigHandler:getString	(Ljava/lang/String;)Ljava/lang/String;
/*     */     //   195: invokevirtual 48	java/lang/StringBuilder:append	(Ljava/lang/String;)Ljava/lang/StringBuilder;
/*     */     //   198: ldc_w 291
/*     */     //   201: invokevirtual 48	java/lang/StringBuilder:append	(Ljava/lang/String;)Ljava/lang/StringBuilder;
/*     */     //   204: invokevirtual 54	java/lang/StringBuilder:toString	()Ljava/lang/String;
/*     */     //   207: astore 6
/*     */     //   209: aload_0
/*     */     //   210: getfield 17	net/craftersland/customenderchest/storage/MysqlSetup:conn	Ljava/sql/Connection;
/*     */     //   213: aload 6
/*     */     //   215: invokeinterface 58 2 0
/*     */     //   220: astore 5
/*     */     //   222: aload 5
/*     */     //   224: invokeinterface 76 1 0
/*     */     //   229: pop
/*     */     //   230: goto +153 -> 383
/*     */     //   233: astore 6
/*     */     //   235: getstatic 192	net/craftersland/customenderchest/EnderChest:log	Ljava/util/logging/Logger;
/*     */     //   238: new 41	java/lang/StringBuilder
/*     */     //   241: dup
/*     */     //   242: ldc_w 293
/*     */     //   245: invokespecial 45	java/lang/StringBuilder:<init>	(Ljava/lang/String;)V
/*     */     //   248: aload 6
/*     */     //   250: invokevirtual 221	java/lang/Exception:getMessage	()Ljava/lang/String;
/*     */     //   253: invokevirtual 48	java/lang/StringBuilder:append	(Ljava/lang/String;)Ljava/lang/StringBuilder;
/*     */     //   256: invokevirtual 54	java/lang/StringBuilder:toString	()Ljava/lang/String;
/*     */     //   259: invokevirtual 248	java/util/logging/Logger:warning	(Ljava/lang/String;)V
/*     */     //   262: aload 6
/*     */     //   264: invokevirtual 80	java/lang/Exception:printStackTrace	()V
/*     */     //   267: aload 4
/*     */     //   269: ifnull +10 -> 279
/*     */     //   272: aload 4
/*     */     //   274: invokeinterface 85 1 0
/*     */     //   279: aload 5
/*     */     //   281: ifnull +10 -> 291
/*     */     //   284: aload 5
/*     */     //   286: invokeinterface 85 1 0
/*     */     //   291: aload_2
/*     */     //   292: ifnull +9 -> 301
/*     */     //   295: aload_2
/*     */     //   296: invokeinterface 295 1 0
/*     */     //   301: aload_3
/*     */     //   302: ifnull +135 -> 437
/*     */     //   305: aload_3
/*     */     //   306: invokeinterface 295 1 0
/*     */     //   311: goto +126 -> 437
/*     */     //   314: astore 8
/*     */     //   316: aload 8
/*     */     //   318: invokevirtual 80	java/lang/Exception:printStackTrace	()V
/*     */     //   321: goto +116 -> 437
/*     */     //   324: astore 7
/*     */     //   326: aload 4
/*     */     //   328: ifnull +10 -> 338
/*     */     //   331: aload 4
/*     */     //   333: invokeinterface 85 1 0
/*     */     //   338: aload 5
/*     */     //   340: ifnull +10 -> 350
/*     */     //   343: aload 5
/*     */     //   345: invokeinterface 85 1 0
/*     */     //   350: aload_2
/*     */     //   351: ifnull +9 -> 360
/*     */     //   354: aload_2
/*     */     //   355: invokeinterface 295 1 0
/*     */     //   360: aload_3
/*     */     //   361: ifnull +19 -> 380
/*     */     //   364: aload_3
/*     */     //   365: invokeinterface 295 1 0
/*     */     //   370: goto +10 -> 380
/*     */     //   373: astore 8
/*     */     //   375: aload 8
/*     */     //   377: invokevirtual 80	java/lang/Exception:printStackTrace	()V
/*     */     //   380: aload 7
/*     */     //   382: athrow
/*     */     //   383: aload 4
/*     */     //   385: ifnull +10 -> 395
/*     */     //   388: aload 4
/*     */     //   390: invokeinterface 85 1 0
/*     */     //   395: aload 5
/*     */     //   397: ifnull +10 -> 407
/*     */     //   400: aload 5
/*     */     //   402: invokeinterface 85 1 0
/*     */     //   407: aload_2
/*     */     //   408: ifnull +9 -> 417
/*     */     //   411: aload_2
/*     */     //   412: invokeinterface 295 1 0
/*     */     //   417: aload_3
/*     */     //   418: ifnull +19 -> 437
/*     */     //   421: aload_3
/*     */     //   422: invokeinterface 295 1 0
/*     */     //   427: goto +10 -> 437
/*     */     //   430: astore 8
/*     */     //   432: aload 8
/*     */     //   434: invokevirtual 80	java/lang/Exception:printStackTrace	()V
/*     */     //   437: return
/*     */     // Line number table:
/*     */     //   Java source line #174	-> byte code offset #0
/*     */     //   Java source line #175	-> byte code offset #7
/*     */     //   Java source line #176	-> byte code offset #9
/*     */     //   Java source line #177	-> byte code offset #11
/*     */     //   Java source line #178	-> byte code offset #13
/*     */     //   Java source line #179	-> byte code offset #16
/*     */     //   Java source line #181	-> byte code offset #19
/*     */     //   Java source line #182	-> byte code offset #29
/*     */     //   Java source line #183	-> byte code offset #53
/*     */     //   Java source line #184	-> byte code offset #62
/*     */     //   Java source line #185	-> byte code offset #98
/*     */     //   Java source line #186	-> byte code offset #111
/*     */     //   Java source line #187	-> byte code offset #119
/*     */     //   Java source line #188	-> byte code offset #122
/*     */     //   Java source line #189	-> byte code offset #146
/*     */     //   Java source line #190	-> byte code offset #155
/*     */     //   Java source line #191	-> byte code offset #173
/*     */     //   Java source line #192	-> byte code offset #209
/*     */     //   Java source line #193	-> byte code offset #222
/*     */     //   Java source line #198	-> byte code offset #230
/*     */     //   Java source line #199	-> byte code offset #235
/*     */     //   Java source line #200	-> byte code offset #262
/*     */     //   Java source line #203	-> byte code offset #267
/*     */     //   Java source line #204	-> byte code offset #272
/*     */     //   Java source line #206	-> byte code offset #279
/*     */     //   Java source line #207	-> byte code offset #284
/*     */     //   Java source line #209	-> byte code offset #291
/*     */     //   Java source line #210	-> byte code offset #295
/*     */     //   Java source line #212	-> byte code offset #301
/*     */     //   Java source line #213	-> byte code offset #305
/*     */     //   Java source line #215	-> byte code offset #311
/*     */     //   Java source line #216	-> byte code offset #316
/*     */     //   Java source line #201	-> byte code offset #324
/*     */     //   Java source line #203	-> byte code offset #326
/*     */     //   Java source line #204	-> byte code offset #331
/*     */     //   Java source line #206	-> byte code offset #338
/*     */     //   Java source line #207	-> byte code offset #343
/*     */     //   Java source line #209	-> byte code offset #350
/*     */     //   Java source line #210	-> byte code offset #354
/*     */     //   Java source line #212	-> byte code offset #360
/*     */     //   Java source line #213	-> byte code offset #364
/*     */     //   Java source line #215	-> byte code offset #370
/*     */     //   Java source line #216	-> byte code offset #375
/*     */     //   Java source line #218	-> byte code offset #380
/*     */     //   Java source line #203	-> byte code offset #383
/*     */     //   Java source line #204	-> byte code offset #388
/*     */     //   Java source line #206	-> byte code offset #395
/*     */     //   Java source line #207	-> byte code offset #400
/*     */     //   Java source line #209	-> byte code offset #407
/*     */     //   Java source line #210	-> byte code offset #411
/*     */     //   Java source line #212	-> byte code offset #417
/*     */     //   Java source line #213	-> byte code offset #421
/*     */     //   Java source line #215	-> byte code offset #427
/*     */     //   Java source line #216	-> byte code offset #432
/*     */     //   Java source line #220	-> byte code offset #437
/*     */     // Local variable table:
/*     */     //   start	length	slot	name	signature
/*     */     //   0	438	0	this	MysqlSetup
/*     */     //   8	115	1	md	java.sql.DatabaseMetaData
/*     */     //   10	402	2	rs1	java.sql.ResultSet
/*     */     //   12	410	3	rs2	java.sql.ResultSet
/*     */     //   14	375	4	query1	java.sql.PreparedStatement
/*     */     //   17	384	5	query2	java.sql.PreparedStatement
/*     */     //   96	7	6	data1	String
/*     */     //   207	7	6	data2	String
/*     */     //   233	30	6	e	Exception
/*     */     //   324	57	7	localObject	Object
/*     */     //   314	3	8	e	Exception
/*     */     //   373	3	8	e	Exception
/*     */     //   430	3	8	e	Exception
/*     */     // Exception table:
/*     */     //   from	to	target	type
/*     */     //   19	230	233	java/lang/Exception
/*     */     //   267	311	314	java/lang/Exception
/*     */     //   19	267	324	finally
/*     */     //   326	370	373	java/lang/Exception
/*     */     //   383	427	430	java/lang/Exception
/*     */   }
/*     */ }


/* Location:              /Users/Server/Desktop/Unpacked Jars/CustomEnderChest-v1.8.0.jar!/net/craftersland/customenderchest/storage/MysqlSetup.class
 * Java compiler version: 7 (51.0)
 * JD-Core Version:       0.7.1
 */